parasail/libparasail.dylib
parasail/bindings_v1.py
parasail/__init__.py
parasail/bindings_v2.py
parasail/include/parasail.h
parasail/include/parasail/cpuid.h
parasail/include/parasail/matrix_lookup.h
parasail/include/parasail/internal_sse.h
parasail/include/parasail/internal_avx.h
parasail/include/parasail/function_lookup.h
parasail/include/parasail/internal_neon.h
parasail/include/parasail/io.h
parasail/include/parasail/memory.h
parasail/include/parasail/internal_altivec.h
parasail/include/parasail/stats.h
parasail/include/parasail/matrices/pam260.h
parasail/include/parasail/matrices/pam430.h
parasail/include/parasail/matrices/pam120.h
parasail/include/parasail/matrices/dnafull.h
parasail/include/parasail/matrices/pam70.h
parasail/include/parasail/matrices/pam360.h
parasail/include/parasail/matrices/pam160.h
parasail/include/parasail/matrices/pam470.h
parasail/include/parasail/matrices/pam220.h
parasail/include/parasail/matrices/pam30.h
parasail/include/parasail/matrices/pam320.h
parasail/include/parasail/matrices/pam170.h
parasail/include/parasail/matrices/pam460.h
parasail/include/parasail/matrices/pam230.h
parasail/include/parasail/matrices/pam20.h
parasail/include/parasail/matrices/pam330.h
parasail/include/parasail/matrices/pam270.h
parasail/include/parasail/matrices/blosum85.h
parasail/include/parasail/matrices/pam420.h
parasail/include/parasail/matrices/pam130.h
parasail/include/parasail/matrices/blosum62.h
parasail/include/parasail/matrices/pam60.h
parasail/include/parasail/matrices/pam370.h
parasail/include/parasail/matrices/nuc44.h
parasail/include/parasail/matrices/blosum35.h
parasail/include/parasail/matrices/pam490.h
parasail/include/parasail/matrices/pam180.h
parasail/include/parasail/matrices/pam280.h
parasail/include/parasail/matrices/blosum75.h
parasail/include/parasail/matrices/pam380.h
parasail/include/parasail/matrices/blosum50.h
parasail/include/parasail/matrices/pam90.h
ont_parasail-1.3.4.dist-info/RECORD
ont_parasail-1.3.4.dist-info/WHEEL
ont_parasail-1.3.4.dist-info/COPYING
ont_parasail-1.3.4.dist-info/top_level.txt
ont_parasail-1.3.4.dist-info/METADATA
